artex_client/__init__.py
artex_client/artex.py
artex_client/connector.py
artex_client/vault.py
artex_client-0.0.1.dist-info/METADATA
artex_client-0.0.1.dist-info/WHEEL
artex_client-0.0.1.dist-info/top_level.txt
artex_client-0.0.1.dist-info/RECORD
