Metadata-Version: 2.4
Name: artex-client
Version: 0.0.1
Summary: Клиентская часть фреймворка ARTEX
Author: FoxVoland, WeeNRizE, ИЦИИ-МИФИ
License: MIT
Requires-Python: >=3.9
